ptestpypi/__init__.py
ptestpypi/sample.py
ptestpypi-1.9.dist-info/DESCRIPTION.rst
ptestpypi-1.9.dist-info/METADATA
ptestpypi-1.9.dist-info/RECORD
ptestpypi-1.9.dist-info/WHEEL
ptestpypi-1.9.dist-info/dependency_links.txt
ptestpypi-1.9.dist-info/metadata.json
ptestpypi-1.9.dist-info/top_level.txt
