Metadata-Version: 2.0
Name: ptestpypi
Version: 1.9
Summary: test app
Home-page: UNKNOWN
Author: Very Good
Author-email: dev@vgs.io
License: MIT License
Platform: UNKNOWN
Classifier: Programming Language :: Python
Requires-Dist: wheel
Requires-Dist: coreapi (==1.20.0)
Requires-Dist: wac (==0.28)
Provides-Extra: tests
Requires-Dist: nose; extra == 'tests'
Requires-Dist: coverage; extra == 'tests'
